pyrrhic/__init__.py
pyrrhic/util.py
pyrrhic/cli/__init__.py
pyrrhic/cli/cat.py
pyrrhic/cli/ls.py
pyrrhic/cli/main.py
pyrrhic/cli/restore.py
pyrrhic/cli/snapshots.py
pyrrhic/cli/state.py
pyrrhic/cli/util.py
pyrrhic/crypto/__init__.py
pyrrhic/crypto/keys.py
pyrrhic/repo/__init__.py
pyrrhic/repo/index.py
pyrrhic/repo/pack.py
pyrrhic/repo/repository.py
pyrrhic/repo/snapshot.py
pyrrhic/repo/tree.py
pyrrhic_restic-0.6.3.dist-info/entry_points.txt
pyrrhic_restic-0.6.3.dist-info/LICENSE
pyrrhic_restic-0.6.3.dist-info/WHEEL
pyrrhic_restic-0.6.3.dist-info/METADATA
pyrrhic_restic-0.6.3.dist-info/RECORD
