Metadata-Version: 2.1
Name: pyrrhic-restic
Version: 0.6.3
Summary: Restic implementation in Python
Author-email: Jürgen Hötzel <juergen@hoetzel.info>
Requires-Python: >=3.7
Classifier: License :: OSI Approved :: MIT License
Requires-Dist: cryptography >= 37.0.4
Requires-Dist: typer[all] >= 0.3.2
Requires-Dist: zstandard
Requires-Dist: msgspec >= 0.9.1
Requires-Dist: pytest ; extra == "test"
Project-URL: Home, https://github.com/juergenhoetzel/pyrrhic
Provides-Extra: test
